time_tracker_cli.py
time_tracker_cli-1.0.1.dist-info/entry_points.txt
time_tracker_cli-1.0.1.dist-info/WHEEL
time_tracker_cli-1.0.1.dist-info/METADATA
time_tracker_cli-1.0.1.dist-info/RECORD
