Metadata-Version: 2.1
Name: time-tracker-cli
Version: 1.0.1
Summary: time-tracker-cli is a Python script that allows you to track the time spent working in your projects or tasks.
Home-page: https://github.com/pazitos10/time-tracker-cli
License: MIT
Keywords: time,tracking,productivity,time tracking
Author: pazitos10
Author-email: pazosbruno@gmail.com
Requires-Python: >=3.6,<4.0
Classifier: License :: OSI Approved :: MIT License
Classifier: Programming Language :: Python :: 3
Classifier: Programming Language :: Python :: 3.10
Classifier: Programming Language :: Python :: 3.6
Classifier: Programming Language :: Python :: 3.7
Classifier: Programming Language :: Python :: 3.8
Classifier: Programming Language :: Python :: 3.9
Requires-Dist: toml (>=0.9,<0.10)
Project-URL: Repository, https://github.com/pazitos10/time-tracker-cli
